<?xml version="1.0" encoding="windows-1250" ?>
<!-- TT2 t³umaczenie trurl3-->
<string_table>
	<string id="ars-ak47">
		<text>AK-47</text>
	</string>
	<string id="ars-ak47_camo1">
		<text>AK-47 Kamufla¿</text>
	</string>
	<string id="ars-ak47_m1">
		<text>AK-47 Mini-Dragunow</text>
	</string>
	<string id="ars-aks47">
		<text>AKS-47</text>
	</string>
	<string id="ars-ak74">
		<text>AK-74</text>
	</string>
	<string id="ars-aks74">
		<text>AKS-74</text>
	</string>
	<string id="ars-aks74_m1">
		<text>AKS-74 Kobra</text>
	</string>
	<string id="ars-aks74_m1_camo1">
		<text>AKS-74 Kobra-Kamuflarz</text>
	</string>
	<string id="ars-ak74m">
		<text>AK-74M</text>
	</string>
	<string id="ars-ak101">
		<text>AK-101</text>
	</string>
	<string id="ars-ak102">
		<text>AK-102</text>
	</string>
	<string id="ars-ak103">
		<text>AK-103</text>
	</string>
	<string id="ars-ak104">
		<text>AK-104</text>
	</string>
	<string id="ars-ak105">
		<text>AK-105</text>
	</string>
	<string id="ars-ak107">
		<text>AK-107</text>
	</string>
	<string id="ars-ak108">
		<text>AK-108</text>
	</string>
	<string id="ars-akm">
		<text>AKM</text>
	</string>
	<string id="ars-akms">
		<text>AKMS</text>
	</string>
	<string id="ars-aks74u">
		<text>AKS-74U</text>
	</string>
	<string id="ars-aks74u_m1_camo1">
		<text>AKS-74U Szturmowy</text>
	</string>
	<string id="ars-an94">
		<text>AN-94 Abakan</text>
	</string>
	<string id="ars-ak5">
		<text>Bofors AK5</text>
	</string>
	<string id="ars-aug_a1">
		<text>Steyr AUG A1 (AUG-77)</text>
	</string>
	<string id="ars-aug_a2">
		<text>Steyr AUG A2</text>
	</string>
	<string id="ars-famas_f1">
		<text>FA MAS F1</text>
	</string>
	<string id="ars-famas_g2">
		<text>FA MAS G2</text>
	</string>
	<string id="ars-famas_p3">
		<text>FAMAS Prototype3</text>
	</string>
	<string id="ars-fnc">
		<text>FN FNC</text>
	</string>
	<string id="ars-g36">
		<text>HK G36</text>
	</string>
	<string id="ars-g36c">
		<text>HK G36C (Compact\Commando)</text>
	</string>
	<string id="ars-g36e">
		<text>HK G36E (Export)</text>
	</string>
	<string id="ars-g36k">
		<text>HK G36K (Kurz)</text>
	</string>
	<string id="ars-galil_ar">
		<text>IMI Galil AR</text>
	</string>
	<string id="ars-galil_arm">
		<text>IMI Galil ARM</text>
	</string>
	<string id="ars-galil_mar">
		<text>IMI Galil MAR</text>
	</string>
	<string id="ars-hk416">
		<text>HK 416</text>
	</string>
	<string id="ars-lr300ml">
		<text>Z-M LR300 ML</text>
	</string>
	<string id="ars-m4a1">
		<text>Colt M4A1</text>
	</string>
	<string id="ars-m16a1">
		<text>Colt M16A1</text>
	</string>
	<string id="ars-m16a2">
		<text>Colt M16A2</text>
	</string>
	<string id="ars-m16a3">
		<text>Colt M16A3</text>
	</string>
	<string id="ars-m16a4">
		<text>Colt M16A4</text>
	</string>
	<string id="ars-vz58">
		<text>CZ SA Vz.58</text>
	</string>
	<string id="ars-rk95">
		<text>Valmet Rk.95</text>
	</string>
	<string id="ars-rk95_camo1">
		<text>Valmet Rk.95 Kamufla¿</text>
	</string>
	<string id="ars-sg550">
		<text>SIG SG550</text>
	</string>
	<string id="ars-sg551">
		<text>SIG SG551</text>
	</string>
	<string id="ars-sg552">
		<text>SIG SG552 Commando</text>
	</string>
	<string id="ars-xm8">
		<text>HK XM8</text>
	</string>
	<string id="ars-xm177e2">
		<text>Colt XM177E2</text>
	</string>
	<string id="ars-mg36">
		<text>HK MG36</text>
	</string>
	<string id="ars-rpk74">
		<text>RPK-74</text>
	</string>
	<string id="ars-xm8_para">
		<text>HK XM8 Para</text>
	</string>
	<string id="ars-aps">
		<text>APS</text>
	</string>
	<string id="ars-beretta92">
		<text>Beretta 92</text>
	</string>
	<string id="ars-cz52">
		<text>CZ.52</text>
	</string>
	<string id="ars-deagle">
		<text>Destert Eagle .50AE</text>
	</string>
	<string id="ars-fort12">
		<text>Fort-12</text>
	</string>
	<string id="ars-glock18c_sk1">
		<text>Glock 18C</text>
	</string>
	<string id="ars-glock18c_sk2">
		<text>Glock 18C Expert</text>
	</string>
	<string id="ars-gsh18">
		<text>GSz-18</text>
	</string>
	<string id="ars-m1911a1">
		<text>Colt Government M1911A1</text>
	</string>
	<string id="ars-m1935hp_mk3">
		<text>FN Browning M1935 High-Power Mk.III</text>
	</string>
	<string id="ars-mp444-9x18">
		<text>MP-444 Bagira 9x18</text>
	</string>
	<string id="ars-mp444-9x19">
		<text>MP-444 Bagira 9x19</text>
	</string>
	<string id="ars-oc33">
		<text>OC-33 Piernacz</text>
	</string>
	<string id="ars-p38">
		<text>Walther P.38</text>
	</string>
	<string id="ars-p99">
		<text>Walther P.99</text>
	</string>
	<string id="ars-p220">
		<text>SIG-SAUER P220</text>
	</string>
	<string id="ars-pb">
		<text>PB</text>
	</string>
	<string id="ars-pm">
		<text>PM</text>
	</string>
	<string id="ars-tt33">
		<text>TT-33</text>
	</string>
	<string id="ars-usp45c">
		<text>HK USP-45 Compact</text>
	</string>
	<string id="ars-sayga12k">
		<text>Sajga 12K</text>
	</string>
	<string id="ars-ppd40">
		<text>PPD-40</text>
	</string>
	<string id="ars-ppsh41">
		<text>PPSz-41</text>
	</string>
	<string id="ars-sr25_mk11_mod0">
		<text>Knights SR25 Mk.11 Mod.0</text>
	</string>
	<string id="ars-hk417">
		<text>HK 417 Sniper</text>
	</string>

	<string id="ars-galatz">
		<text>IMI GALATZ</text>
	</string>
	<string id="ars-svd">
		<text>SWD</text>
	</string>
	<string id="ars-acog">
		<text>Celownik ACOG</text>
	</string>
	<string id="ars-aug_a1_scope">
		<text>Obiektyw AUG-77 Optics</text>
	</string>
	<string id="ars-g36_scope">
		<text>Obiektyw G36 Optics</text>
	</string>
	<string id="ars-scope1">
		<text>Optyka M16</text>
	</string>
	<string id="ars-sil_9_p">
		<text>T³umik M9-P</text>
	</string>
	<string id="ars-sil_762_p">
		<text>T³umik M7.62-P</text>
	</string>
	<string id="ars-sil_9_pb">
		<text>T³umik 6P9</text>
	</string>
	<string id="ars-sil_545_ar">
		<text>T³umik M5.45-A</text>
	</string>
	<string id="ars-sil_556_ar">
		<text>T³umik M5.56-A</text>
	</string>
	<string id="ars-sil_762_ar">
		<text>T³umik M7.62-A</text>
	</string>
	<string id="ars-sil_762_pms">
		<text>T³umik M7.62-PMS</text>
	</string>
	<string id="ars-sil_1143_p">
		<text>T³umik M11.43-P</text>
	</string>
	<string id="ars-50_ae">
		<text>.50 AE</text>
	</string>
	<string id="ammo-7.62x25-p">
		<text>7.62x25 mm P</text>
	</string>
	<string id="ammo-7.62x25-ps">
		<text>7.62x25 mm PS</text>
	</string>
	<string id="ars-7.62x39_fmj">
		<text>7.62x39 mm CMO</text>
	</string>
	<string id="ars-7.62x39_ap">
		<text>7.62x39 mm BP</text>
	</string>
	<string id="ars-7.62x51_fmj">
		<text>7.62x51 mm NATO</text>
	</string>
	<string id="ars-7.62x51_ap">
		<text>7.62x51 mm NATO BP</text>
	</string>
	<string id="enc_arsenal_ak47">
		<text>Automat Ka³asznikowa wzór 1947 roku, pod nabój 7.62x39 mm. Automat-klasyka, znany na ca³ym œwiecie. Ceniony w Zonie za niezawodnoœæ nawet w najbardziej niesprzyjaj¹cych warunkach i jednoczeœnie za ³atwoœæ w  u¿ytkowaniu. Mo¿na spotkaæ zarównao u niedawno prtzyby³ych do Zony stalkerów, jak i u weteranów.</text>
	</string>
	<string id="enc_arsenal_ak47_camo1">
		<text>AK-47, z naniesionym wzorem kamufla¿u.</text>
	</string>
	<string id="enc_arsenal_ak47_m1">
		<text>Mini-Dragunow - dziecko rumuñskich rusznikarzy, zbudowany na bazie AK-47. Jest to automat, wykonany w formie karabinu snajperskiego.</text>
	</string>
	<string id="enc_arsenal_aks47">
		<text>Automat Ka³asznikowa sk³adany wzór 1947 roku, pod nabój 7.62x39 mm. Automat-klasyka, znany na ca³ym œwiecie. Ceniony w Zonie za niezawodnoœæ nawet w najbardziej niesprzyjaj¹cych okolicznoœciach i jednoczeœnie za ³atwoœæ w  u¿ytkowaniu, szczególnie dziêki jego ma³ym wymiarom w stanie z³ozonym. Mo¿na spotkaæ zarówno u niedawno przyby³ych do Zony stalkerów, jak i u weteranów.</text>
	</string>
	<string id="enc_arsenal_ak74">
		<text>Automat Ka³asznikowa wzór 1974 roku, pod nabój 5.45x39 mm. Ceniony w Zonie za niezawodnoœæ nawet w najbardziej niesprzyjaj¹cych okolicznoœciach i jednoczeœnie za ³atwoœæ w  u¿ytkowaniu. Mo¿na spotkaæ zarówno u niedawno przyby³ych do Zony stalkerów, jak i u weteranów.</text>
	</string>
	<string id="enc_arsenal_aks74">
		<text>Automat Ka³asznikowa sk³adany wzór 1974 roku, pod nabój 5.45x39 mm. Ceniony w Zonie za niezawodnoœæ nawet w najbardziej niesprzyjaj¹cych okolicznoœciach i jednoczeœnie za ³atwoœæ w  u¿ytkowaniu. Mo¿na spotkaæ zarówno u niedawno przyby³ych do Zony stalkerów, jak i u weteranów.</text>
	</string>
	<string id="enc_arsenal_aks74_m1">
		<text>Automat Ka³asznikowa AKS-74 z zainstalowanym celownikiem kolimatorowym "Kobra EKR-8-02"</text>
	</string>
	<string id="enc_arsenal_aks74_m1_camo1">
		<text>Automat Ka³asznikowa AKS-74 z zainstalowanym celownikiem kolimatorowym "Kobra EKR-8-02", i naniesionym wzorem maskuj¹cym.</text>
	</string>
	<string id="enc_arsenal_ak74m">
		<text>PóŸniejszy wariant automatu Ka³asznikowa AK-74, przyjêty na uzbrojenie Rosujskiej Armii na pocz¹tku lat 1990ch. Od wczeœniejszej wersji odró¿nia siê sk³adana na bok plastykow¹ kolb¹ i szyn¹ do mocowania urz¹dzeñ celowniczych po lewej stronie komory. Dobry automat do nocnych rajdów w Zonie poniewa¿ wykonany jest w czarnym kolorze.</text>
	</string>
	<string id="enc_arsenal_ak101">
		<text>Ten automat, jak i ca³a "setna" seria automatów Ka³asznikowa, przeznaczony jest w pierwszym rzêdzie na eksport. Jest modyfikacj¹ AK-74M pod NATOwski nabój 5.56x45.</text>
	</string>
	<string id="enc_arsenal_ak102">
		<text>"Skrócony" AK-101. Lekki, wygodny, niezawodny - bardzo dobry wybór.</text>
	</string>
	<string id="enc_arsenal_ak103">
		<text>Ten automat, jak i ca³a "setna" seria automatów Ka³asznikowa, przeznaczony jest w pierwszym rzêdzie na eksport. Jest modyfikacj¹ AK-74M pod radziecki nabój 7.62x39.</text>
	</string>
	<string id="enc_arsenal_ak104">
		<text>"Skrócony" AK-103. Lekki, wygodny, niezawodny - bardzo dobry wybór.</text>
	</string>
	<string id="enc_arsenal_ak105">
		<text>"Skrócony" AK-74M. Lekki, wygodny, niezawodny - bardzo dobry wybór.</text>
	</string>
	<string id="enc_arsenal_ak107">
		<text>Automat, wykonany w systemie balansowania energii odrzutu. Du¿a szybkostrzelnoœæ, dok³adnoœc i celnoœæ ognia automatycznego. Przewidziany pod rodzimy nabój 5.45x39.</text>
	</string>
	<string id="enc_arsenal_ak108">
		<text>Automat, wykonany w systemie balansowania energii odrzutu. Du¿a szybkostrzelnoœæ, dok³adnoœc i celnoœæ ognia automatycznego. Przewidziany pod NATOwski nabój 5.56x45.</text>
	</string>
	<string id="enc_arsenal_akm">
		<text>Automat Ka³asznikowa modernizowany, pod nabój 7.62x39 mm. Ceniony w Zonie za niezawodnoœæ nawet w najbardziej niesprzyjaj¹cych okolicznoœciach i jednoczeœnie za ³atwoœæ w  u¿ytkowaniu. Mo¿na spotkaæ zarówno u niedawno przyby³ych do Zony stalkerów, jak i u weteranów.</text>
	</string>
	<string id="enc_arsenal_akms">
		<text>Automat Ka³asznikowa modernizowany, sk³adany, pod nabój 7.62x39 mm. Ceniony w Zonie za niezawodnoœæ nawet w najbardziej niesprzyjaj¹cych okolicznoœciach i jednoczeœnie za ³atwoœæ w  u¿ytkowaniu. Mo¿na spotkaæ zarówno u niedawno przyby³ych do Zony stalkerów, jak i u weteranów.</text>
	</string>
	<string id="enc_arsenal_aks74u">
		<text>Skrócony automat Ka³asznikowa wzór 1974 roku, pod nabój 5.45x39 mm. Z masy i rozmiarów bliski pistoletom automatycznym, jednak¿e zasada dzia³ania mechanizmu tej broni i zastosowana w niej amunicja czynia go przedstawicielem klasy automatów. Do zalet nale¿¹ ma³e wymiary, sczagólnie wygodne przy prowadzeniu walk w mieœcie, i stosunkowo wysoka si³a przebijaj¹ca naboju. G³ówne wady - ma³¹ donoœnoœæ celowana i sk³onnoœæ do szybkiego przegrzewania siê przy strzelaniu seriami.</text>
	</string>
	<string id="enc_arsenal_aks74u_m1_camo1">
		<text>Modyfikacja AKS-74U. Zamontowany celownik kolimatorowy "Kobra EKR-8-02", naniesiony wzór kamufla¿u. D³u¿sza lufa pozwala na instalacjê granatnika podwieszonego GP-25 "Ognisko".</text>
	</string>
	<string id="enc_arsenal_an94">
		<text>Automat Nikonowa wzór 1994 roku. Wykonay w systemie gromadzenia energii odrzutu. Bardzo celna broñ przy strzelaniu seriami po dwa pociski.</text>
	</string>
	<string id="enc_arsenal_ak5">
		<text>Ten karabin znajduje siê na uzbrojeniu armii Szwecji. Zbudowany na bazie belgijskiego karabinu FN FNC.</text>
	</string>
	<string id="enc_arsenal_aug_a1">
		<text>Austriacki karabin automatyczny, z niezdejmowanym celownikiem optycznym o powiêkszeniu 1.5x i wykonany w systemie "bull-pup".</text>
	</string>
	<string id="enc_arsenal_aug_a2">
		<text>Austriacki karabin automatyczny, ze zointegrowana szyn¹ Picatinny i wykonany w systemie "bull-pup".</text>
	</string>
	<string id="enc_arsenal_famas_f1">
		<text>Pierwszy z serii automatów FA MAS francuskiej konstrukcji. Du¿a szybkostrzelnoœæ i schemat "bull-pup" spowodowa³y jego spor¹ popularnoœæ poœród zwolenników zagranicznej broni.</text>
	</string>
	<string id="enc_arsenal_famas_g2">
		<text>Modyfikacja automatu FA MAS F1 ze standardowym NATOwskim magazynkiem od M16 na 30 naboi. Du¿a szybkostrzelnoœæ i schemat "bull-pup" uczyni³y go doœæ popularnym wzorem broni palnej.</text>
	</string>
	<string id="enc_arsenal_famas_p3">
			<text>Prototyp nowego automatu z serii FAMAS. Bardzo rzadka broñ w Zonie.</text> 
	</string>
	<string id="enc_arsenal_fnc">
		<text>Belgijski karabin, w latach 1980-ch eksportowany jako uzbrojenie róznychformacji policyjnych, w tym tak¿e w USA. Zgodnie z opiniami, FNC jest bronia niezawodna i wygodn¹, z dobrymi cechami bojowymi. W zasadniczych charakterystykach nie ustêpuje innym karabinom skonstruowanym w tym czasie, jednak¿e do chwili jego pojawienia siê na rynku czêœæ niszy by³a ju¿ zajêta przez inne modele, co wyjasnie jego niezbyt szerokie rozprzestrzenienie.</text>
	</string>
	<string id="enc_arsenal_g36">
		<text>Karabin szturmowy G36 opracowany przez niemieck¹ firmê Heckler und Koch GmbH na pocz¹tku lat 1990ch pod wewnêtrznym oznaczeniem  HK 50. W 1995 roku G36 by³ przyjety na uzbrojenie Bundeswehry, a w 1999 - na uzbroneie si³ zbrojnych Hiszpanii. Jest jednym z lepszych przykladów broni automatycznej - ergonomiczny, precyzyjkny i niezawodny.</text>
	</string>
	<string id="enc_arsenal_g36c">
		<text>Modyfikacja niemieckiego karabinu szturmowego G36, z uniwersaln¹ szyn¹ Picatinny i krótka luf¹\³o¿em.</text>
	</string>
	<string id="enc_arsenal_g36e">
		<text>Eksportowy wariant niemieckiego karabinu szturmowego G36, bez wbudowanego celownika kolimatorowego.</text>
	</string>
	<string id="enc_arsenal_g36k">
		<text>Modyfikacja niemieckiego karabinu szturmowego G36, z uniwersaln¹ szyn¹ Picatinny i krótsz¹ luf¹\³o¿em.</text>
	</string>
	<string id="enc_arsenal_galil_ar">
		<text>Izraelski automat, dla którego jako wzorzec pos³u¿y³ doskona³y automat Ka³asznikowa. Broñ niezawodna i ma³o wymagaj¹ca.</text>
	</string>
	<string id="enc_arsenal_galil_arm">
		<text>Izraelski automat, dla którego jako wzorzec pos³u¿y³ doskona³y automat Ka³asznikowa. Wykonany w odmianie rêcznego karabinu maszynowaego ze sk³adanymi nó¿kami. Broñ niezawodna i ma³o wymagaj¹ca.</text>
	</string>
	<string id="enc_arsenal_galil_mar">
		<text>Skrócony wariant izraelskiego automatu IMI Galil AR.</text>
	</string>
	<string id="enc_arsenal_hk416">
		<text>Karabin szturmowy (automat) HK416 zewnêtrznie podobny do automatów serii AR15\M16\M4, ale wykonany na zasadzie automatyki odprowadzania gazów z krótkim skokiem umieszczonego nad luf¹ t³oka gazowego, zapozyczonej z niemieckiego karabinu G36. Dziêki temu uda³o siê osi¹gn¹æ wiêksz¹ niezawodnoœæ bezawaryjnoœc modelu.</text>
	</string>
	<string id="enc_arsenal_lr300ml">
		<text>Dalsze rozwiniêcie karabinu szturmowego AR15\M16. Odznacza siê niez³ymi czarakterystykami taktyczno-technicznymi.</text>
	</string>
	<string id="enc_arsenal_m4a1">
		<text>Ten karabin by³ opracowany w roku 1996 na zamówienie operacyjnych si³ specjalnych na bazie karabinu M16A3, i odznacza siê powrotem do ognia w pe³ni automatycznego w miejsce stylu prowadzenia ognia seriami po 3 pociski.</text>
	</string>
	<string id="enc_arsenal_m16a1">
		<text>Na pocz¹tku lat 1970-ch karabin M16 by³ ceniona bronia bojow¹, posiadaj¹c¹ szereg istotnych zalet (ale i niedoci¹gnêcia, oczywiœcie, te¿ by³y). W porównaniu z g³ównym konkurentem M16 na rynku œweiatowym - automatem Ka³asznikowa (AKM), M16 posiada³ wiêksz¹ dok³adnoœæ i celnoœæ ognia ppojedynczymi strza³ami, by³ wygodniejszy przyjemniejszy w u¿yciu. Z drugiej strony, M16 wymaga³ znacznie uwa¿niejszej obs³ugi, i lepszej jakoœciowo amunicji.</text>
	</string>
	<string id="enc_arsenal_m16a2">
		<text>Dalsza modyfikacja karabinu M16A1. Posiada ciê¿sz¹ lufê, wprowadzono styl strzelania seriami po trzy pociski, zamist ognia w pe³ni automatycznego, a tak¿e pojemniejszy magazynek na 30 nabojów i zintegrowany celownik optyczny.</text>
	</string>
	<string id="enc_arsenal_m16a3">
		<text>Dalsza modyfikacja karabinu M16A1. Posiada ciê¿sz¹ lufê, wprowadzono styl strzelania seriami po trzy pociski, zamist ognia w pe³ni automatycznego, a tak¿e pojemniejszy magazynek na 30 nabojów.</text>
	</string>
	<string id="enc_arsenal_m16a4">
		<text>Dalsza modyfikacja karabinu M16A1. Posiada ciê¿sz¹ lufê, wprowadzono styl strzelania seriami po trzy pociski, zamist ognia w pe³ni automatycznego, a tak¿e pojemniejszy magazynek na 30 nabojów.</text>
	</string>
	<string id="enc_arsenal_vz58">
		<text>Ta broñ, zewnêtrznie podobna do  automatu Ka³asznikowa, jest w³asnym opracowaniem czeskich rusznikarzy. W porównaniu z AK ma wy¿sz¹ szybkostrzelnoœæ.</text>
	</string>
	<string id="enc_arsenal_rk95">
		<text>Ten model jest rozwiniêciem fiñskiego automatu Valmet Rk.62, który z kolei jest licencyjna kopi¹ AK-47, ze zmianami ergonomicznymi.</text>
	</string>
	<string id="enc_arsenal_rk95_camo1">
		<text>Ten model jest rozwiniêciem fiñskiego automatu Valmet Rk.62, który z kolei jest licencyjna kopi¹ AK-47, ze zmianami ergonomicznymi. Wariant "z kamufla¿em".</text>
	</string>
	<string id="enc_arsenal_sg550">
		<text>Szwajcarski karabin, opracoewany na pocz¹tku lat 1980-ch. Wygodna, niezawodna i celna broñ.</text>
	</string>
	<string id="enc_arsenal_sg551">
		<text>Skrócony wariant szwajcarskiego karabinu SIG SG550.</text>
	</string>
	<string id="enc_arsenal_sg552">
		<text>Skrócony wariant automatu SIG SG550.</text>
	</string>
	<string id="enc_arsenal_xm8">
		<text>Karabin, któy o ma³o co nie zamieni³ M16A2  w amerykañskiej armii. Bardzo rzadki model broni palnej, odznaczaj¹cy siê dobrymi w³asnoœciami bojowymi.</text>
	</string>
	<string id="enc_arsenal_xm177e2">
		<text>Karabin, przyjêty na uzbrojenie szeregu oddzia³ów armii USA, jako zamiana dla kompaktowego CAR-15.</text>
	</string>
	<string id="enc_arsenal_mg36">
		<text>Rêczny karabin maszynowy, skonstruowany na bazie niemieckiego karabinu szturmowego G36. Wykorzystuje bêbnowy magazyn na 100 nabojów.</text>
	</string>
	<string id="enc_arsenal_rpk74">
		<text>Rêczny karabin maszynowy Ka³asznikowa wzoru 1974 roku z dyskowym magazynem na 75 nabojów.</text>
	</string>
	<string id="enc_arsenal_xm8_para">
		<text>Wariant automatu XM8 z magazynem bêbnowym i ciê¿sz¹ luf¹, co przekszta³ca tê broñ w pe³nosprawny karabin maszynowy.</text>
	</string>
	<string id="enc_arsenal_aps">
		<text>Pistolet APS by³ opracowany pod koniec lat 1940-ch - pocz¹tku 1950-ch przez konstruktora I. Ja. Steczkina i zosta³ przyjêty na uzbrojenie Armii Radzieckiej w 1951 roku, jednoczesnie z poistoletem Makarowa PM. APS (Automatyczny Pistolet Steczkina) by³ przeznaczony do osobistej samoobrony tych kategorii oficerów wojska, którym wed³ug regulaminu nie przys³ugiwa³ automat albo karabin.</text>
	</string>
	<string id="enc_arsenal_beretta92">
		<text>Pistolet w³oskiego opracowania, przyjêty na uzbrojenie armii USA. Ca³a seria pistoletów Beretta 92 ma zas³u¿on¹ reputacjê ca³kiem niezwodnej, chocia¿ nieco niewygodnej broni.</text>
	</string>
	<string id="enc_arsenal_cz52">
		<text>Pistolet, opracowany w 1952 roku na uzbrojenie armii Czechos³owacji.</text>
	</string>
	<string id="enc_arsenal_deagle">
		<text>Bardzo interesuj¹cy egzemplarz broni palnej, który by³ pokazywany w mnóstwie filmów i gier, i który zdoby³ ogromna popularnoœæ. Pistolet Desert Eagle wykorzystuje bardzo rzadk¹ dla pistoletów opcjê automatyki z zamykaniem lufy ruchem powrotnym zamka i wykorzystaniem energii odprowadzanych z lufy gazów do prze³adowywania. Potê¿ny pistolet, z bardzo silnym odrzutem.</text>
	</string>
	<string id="enc_arsenal_fort12">
		<text>Pistolet ukraiñskiej produkcji, przyjêty  na uzbrojenie jako zamiennik moralnie przestarza³ego radzieckiego pistoletu Makarowa. W charakterze podstawowej amunuicji zosta³ wykorzystany dostepny i dobrze poznany nabój  9x18PM, pomimo tego nowy pistolet powinien by³ zapewniæ, w porównmaniu z PM, wiêksz¹ dok³adnoœc strzelania i moc ogniow¹(dziêki wiêkszej pojemnoœci magazynka). Jako wzorzec do konstrukcji  zosta³ wybrany czeski pistolet CZ-83, i w Czechos³owacji zosta³o zakupione odpowiedznie oprzyrz¹dowanie do produkcji pistoletów.</text>
	</string>
	<string id="enc_arsenal_glock18c_sk1">
		<text>Pistolet Glock 18 (18 - od pojemnoœci magazynka na 18 naboi) by³ opracowany przez austriacka firmê Glock dla armii Austrii, przy czym by³a to pierwsza próba skonstruowania pistoletu w tej firmie. Tym niemniej, pistolet okaza³ siê wyj¹tkowo udany, niezawodny i wygodny, i zosta³ przyjêty na uzbrojenie armiii austriackiej. Ten model ma prze³¹cznik rodzaju strza³u i umo¿liwia strzelanie seriami po trzy naboje.</text>
	</string>
	<string id="enc_arsenal_glock18c_sk2">
		<text>Pistolet Glock 18 (18 - od pojemnoœci magazynka na 18 naboi) by³ opracowany przez austriacka firmê Glock dla armii Austrii, przy czym by³a to pierwsza próba skonstruowania pistoletu w tej firmie. Tym niemniej, pistolet okaza³ siê wyj¹tkowo udany, niezawodny i wygodny, i zosta³ przyjêty na uzbrojenie armiii austriackiej. Ten model wyposa¿ono w magazynek o pojemnoœci 31 naboi i prze³acznik rodzaju ognia umo¿liwiaj¹cy strzelanie w pe³ni automatyczne.</text>
	</string>
	<string id="enc_arsenal_gsh18">
		<text>Pistolet GSz-18 by³ opracowany pod koniec lat 1990-ch  w tulskich zak³adach zbrojeniowych pod przewodnictwem znanych konstruktorów uzbrojenia (w szczególnoœci - dzia³ek lotniczych) Graziewa i Szipunowa. Liczba 18 w nazwie oznacza pojemnoœc magazynka. Do zalet GSz-18 mo¿na zaliczyæ bardzo ma³¹ dla swojej klasy wagê, wiêksz¹ pojemnoœc magazynka, niskie po³o¿enie lufy w stosunku do reki strzelaj¹cego, dobr¹ celnoœæ strza³u. </text>
	</string>
	<string id="enc_arsenal_m1911a1">
		<text>Legendarny "Colt", który do tej pory znajduje siê na wyposa¿enieu wielu krajów. Nale¿y zaznaczyæ, ¿e jak wczeœniej, tak i teraz, pistolety danej konstrukcji podukowane s¹ nie tylko przez firmjê Colt. Zarówno w wyjœciowym Brauningowskim wariancie jak i z ró¿nymi modyfikacjami, produkuje je dziesi¹tki, jeœli nie setki firm na ca³ym œwiecie.</text>
	</string>
	<string id="enc_arsenal_m1935hp_mk3">
		<text>Wspólczesna modyfikacja belgijskiego pistoletu FN Browning HP (High Power 1935), produkowanego od 1935 roku.</text>
	</string>
	<string id="enc_arsenal_mp444-9x18">
		<text>Pistolet MP-444 przeznaczony na wyposa¿enie armii i policji. Praca automatyki pistoletu oparta jest na zasadzie krótkiego ruchu lufy. Wyposa¿ony w lufê, przewidzian¹ na rodzimy nabój 9x18.</text>
	</string>
	<string id="enc_arsenal_mp444-9x19">
		<text>Pistolet MP-444 przeznaczony na wyposa¿enie armii i policji. Praca automatyki pistoletu oparta jest na zasadzie krótkiego ruchu lufy. Wyposa¿ony w lufê, przewidzian¹ na nabój 9x19.</text>
	</string>
	<string id="enc_arsenal_oc33">
		<text>Pistolet OC-33 by³ opracowany w po³owie lat 1990-ch w CKIW SOO (Centralne Zaklady Zbrojeniowe Broni Sportowej i Myœliwskiej) pod przewodnictwem I. Ja. Steczkina dla zamiany przestarzalego i dawno zdjêtego z produkcji pistoletu APS konstrukcji tego¿ autora. Pistolet OC-33 - broñ automatyczna, zbudowana na zasadzie automatyki z otwartym zamkiem. Dla zmniejszenia przwidywanego odrzutu lufa pistoletu jest ruchoma. W koñcówce cyklu odrzutu zamek chwyta masywn¹ lufê, i dziêki jej inercji nastepuje wstêpne hamowanie zamka przed jego uderzeniem w ramê w koñcowym tylnym po³o¿eniu.</text>
	</string>
	<string id="enc_arsenal_p38">
		<text>Pistolet P.38 by³ opracowany jeszcze w drugiej po³owie lat trzydziestych specjalnie jako pistolet wojskowy. Jego pierwszym uzytkownikiem by³a Szwecja, która w 1938 roku zakupi³a niwielka iloœæ pistoletów Walther HP (Heeres Pistole, to znaczy pistolet wojskowy), w 1940 roku ten pistolet pod oficjalnym oznaczeniem Pistole 38 by³ przyjêty na uzbrojenie Wehrmachtu i by³ szeroko stosowany w czasie Drugiej Wojny Œwiatowej. Walther P.38 - samopowtarzalny pistolet wyposa¿ony w zamek ryglowany ryglem wahliwym i kurek wewnêtrzny. Automatyka pistoletu zbudowana jest na zasadzied wykorzystania energii krótkiego odrzut lufy.</text>
	</string>
	<string id="enc_arsenal_p99">
		<text>Walther P99 - niemiecki pistolet samopowtarzalny, produkowany na licencji w Polsce przez Fabrykê Broni "£ucznik" (dawne Zak³ady Mechaniczne "£ucznik"). Dzia³a na zasadzie krótkiego odrzutu lufy, zamek ryglowany przez przekoszenie lufy w p³aszczyŸnie pionowej w systemie Browning-Petter. W pistolecie zastosowano mechanizm spustowy z samonapinaniem typu Double Action. P99 nie posiada zewnêtrznych bezpieczników. Do zasilania stosuje siê magazynki wymienne pude³kowe, dwurzêdowe, z jednopozycyjnym wyprowadzeniem o pojemnoœci 16 nabojów. Pistolet posiada sta³e przyrz¹dy celownicze i wskaŸnik napiêcia iglicy oraz wskaŸnik obecnoœci naboju w komorze nabojowej.</text>
	</string>
	<string id="enc_arsenal_p220">
		<text>Opracowanie nowego wojskowego pistoletu dla armii szwajcarskiej na zamianê bardzo dobrego, ale bardzo drogiego i moralnie przestarza³ego pistoletu SIG P210 rozpoczê³o siê na pocz¹tku lat 1970-ch. Zgodnie z zapotrzebowaniem armii, nowy pistolet powinien posiadaæ tradycyjn¹ dla szweajcarskiej broni wysok¹ niezawodnoœæ i dok³adnoœc strzelania, niewielk¹ masê, samopowtarzalny mechanizm spustowy, i co isttne, umiarkowan¹ cenê. Znana szwajcarska kompania SIG opracowa³a i pistolet, i w po³owie lat 1970-ch zosta³ on przyjêty na uzbrojenie pod oznaczeniem Pistole 75. Pistolet P220 wkorzystuje do prze³adowania energiê krótkiego odrzutu lufy . Ryglowanie lufy odbywa siê wed³ug zmodyfikowanego systemu Brauninga jednym masywnym wystêpem na lufie za okno wyrzucania ³usek w korpusie zamka..</text>
	</string>
	<string id="enc_arsenal_pb">
		<text>Pistolet bezgloœny PB (indeks 6P9) by³ opracowany na bazie pistoletu Makarowa PM dla uzbrojenia wojskowych grup wywiadowczych a tak¿e personelu KGB ZSRR, przyjêty na uzbrojenie w 1967 roku. Pistolet posiada wbudowany t³umik, przy czym w odróznieniu od wiêkszoœci analogicznych systemów t³umik dŸwieku wystrza³u zrobiono rozbierany na dwie czêœci. Takie rozwi¹zanie pozwala nosiæ i przechowywaæ pistolet ze zdjêt¹ przedni¹ czêsci¹ t³umika (nasadk¹), a przed u¿yciem szybko zak³adaæ nasadkê na broñ. Przy tym pistolet zachowuje mo¿liwoœæ bezpiecznego dla strzelaj¹cego prowadzenia ognia ze zdjêt¹ nasadk¹, co mo¿e byc istotne w krytycznych momentach.</text>
	</string>
	<string id="enc_arsenal_pm">
		<text>Pistolet systemu Makarowa by³ opracowany w odpowiedzi na zapotrzebowanie Radzieckiej Armii na skonstruowanie nowego pistoletu dla samoobrony kadry oficerskiej, mniejszego i bezpieczniejszego w stosowaniu ni¿  pistolet Tokariewa TT, ale przy tym posiadaj¹cego wiêksz¹ si³ê obalaj¹c¹ pocisku.</text>
	</string>
	<string id="enc_arsenal_tt33">
		<text>Pistolet TT (Tulski, Tokariewa), jak wynika z jego nazwy, by³ opracowany w Tulskim Zak³adzie Zbrojeniowym przez legendarnego rosyjskiego rusznikarza Fiodora Tokariewa i przyjêty na uzbrojenie Armii Czerwonej w 1933 roku. Na swój czas pistolet TT by³ doœæ zaawansowana broni¹, mocn¹¿ i niezawodn¹, prost¹ w obs³udze i naprawach. Jego g³ówn¹ wad¹ by³o obni¿enie poziomu bezpieczeñstwa w stosowaniu z powodu braku pe³nych mechanizmów bezpieczeñstwa, stosunkowo niewielka si³a obalaj¹ca lekkiej kuli 7.62mm, i niezbyt wygodna forma rêkojesci.</text>
	</string>
	<string id="enc_arsenal_usp45c">
		<text>Kompaktowa wersja pistoletu USP-45 niemieckiego opracowania. Ca³a seria pistoletów USP odznacza siê wysok¹ niezawodnoœci¹ i ¿ywotnoœci¹, dobr¹ dok³adnoœcia strzelania. Z niewielkich niedostatków mo¿na wymieniæ znaczne rozmiary broni, nawet w wariancie kompaktowym, doœæ wysoko po³o¿ony srodek ciê¿koœci i masywny zamek, nieco utrudniaj¹cy noszenie w ukryciu.</text>
	</string>
	<string id="enc_arsenal_sayga12k">
		<text>G³adkolufowa strzelba Sajga naœladuje ogóln¹ kompozycjê i budowê automatu Ka³asznikowa, z mechanizmem odprowadzania gazów i zamykaniem obrotem zamka. Naturalnie, czêœæ zamkowa i komora by³y przekonstruowane w celu wykorzystania ³adunków myœliwskich, mechanizm uderzeniowo-spustowy pozbawiony jest auto spustu, w mechanizmie odprowadzania gazów pojawi³ siê regulator gazowy dla zapewnienia niuezawodnego prowadzenia ognia. W wariancie Sajga 12K broñ posiada pastikowe ³o¿e, a tak¿e pistoletow¹ rekojeœæ i skladana na lewo plastikow¹ kolbê od automatu AK-74U. W sk³¹d celownika wchodzi muszka na rurce gazowej ponad luf¹. Zasilanie ³adunakami odbywa siê ze specjalnych zdejmowanych pude³kowych magazynków ró¿nej pojemnoœci. Bezpiecznik w swojej konstrukcji jest  analogiczny temu z automatu Ka³asznikowa.</text>
	</string>
	<string id="enc_arsenal_ppd40">
		<text>Pistolet-maszynowy Diegtiariewa by³ opracowany w pierwszej po³owie lat 1930-ch i przyjêty na uzbrojenie w 1935 roku pod oznaczeniem PPD-34. Jest to typowy system pierwszego pokolenia, z drewnianym ³o¿em i szerokim wykorzystaniem maszynowej obróbki metalu w produkcji. Niestety, ówczesne dowództwo Armii Czerwonej nie rozumia³o roli karabinów maszynowych, i dlatego PPD-34, jak i jego póŸniejsza modyfikacja PPD-34/38, produkowane by³y w ma³ych iloœciach i wykorzystywane by³y zasadniczo w pogranicznych oddzia³ach NKWD. Przed sam¹ Wielk¹ Wojn¹ OjczyŸnian¹, w 1940 roku, PPD zosta³ ulepszony, jednak¿e jego konstrukcja okaza³a siê niedostosowana dla masowej produkcji czasu wojny. I ju¿ pod koniec 1941 roku PPD-40 by³ zamieniony na uzbrojeniu Armii Czerwonej nowszym, tañszym i efektywniejszym pistoletem-maszynowym Szpagina PPSz-41. PPD-40 zbudowano na bazie automatyki ze swobodnym zamkiem. Ogieñ prowadzi siê z otwartego zamka.</text>
	</string>
	<string id="enc_arsenal_ppsh41">
		<text>PPSz-41 (Pistolet-naszynowy konstrukcji Szpagina) by³ opracowany w 1941 roku dla zamiany drogiego w produkcji pistoletu-maszynowego Diegtiariewa PPD-40. W tym samym roku przyjêty na uzbrojenie Armii Czerwonej. PPSz-41 by³ prost¹ i tani¹ w produkcji bronia czasu wojny, i by³ produkowany w znacznych iloœciach - w latach wojny wyprodukowano oko³o 5 lub 6 milionów sztuk PPSz-41. Wkrótce po wojnie PPSz-41 by³ zdjêty z uzbrojenia Armii Radzieckiej, jednak¿e by³ w duzych iloœciach eksportowany do prosowiecko nastawionych rozwijaj¹cych siê krajów œwiata, i w Afryce mo¿na go by³o zobaczyæ nawet w latach 1980-ch. Do zalet PPSz nalezy wysoka efektywna donoœnoœæ, prostota i tanioœæ. Z wad nalezy wymieniæ znaczna masê i gabaryty, wysokie tempo strzelania a tak¿e sk³onnoœæ do niekontrolowanych wystrza³ów przy upadku na tward¹ powierzchniê.</text>
	</string>
	<string id="enc_arsenal_sr25_mk11_mod0">
		<text>Karabin SR-25 zosta³ opracowany przez Eugena Stonera (jednego z konstruktorów karabinów Ar-15 / M16) na pocz¹tku lat 1990-ych, kiedy wspó³pracowa³ z amerykañsk¹ kompani¹ Knight's Armaments Co. Karabin SR-25 (Stoner Rifle model 25) sta³ siê podstaw¹ konstrukcji AR-15, zmodyfikowanego do amunicji 7.62x51 NATO. Podstawowym przeznaczeniem karabinów Mk.11 Mod.0 i XM110 jest eliminacja przeciwników na odleg³oœci do 800 metrów. Z taktycznego punktu widzenia, karabiny te s¹ analogami karabinów snajperskich Dragunowa SWD, jednak¿e odznaczaj¹ siê lepsz¹ celnoœci¹ strza³u (w tym tak¿e z powodu wy¿szej jakoœci amunicji) i wiêksz¹ elastycznoœci¹ zastosowañ.</text>
	</string>
	<string id="enc_arsenal_hk417">
		<text>Karabin automatyczny HK 417 kaliber 7.62mm NATO zosta³ opracowany na bazie karabinu automatycznego Heckler-Koch HK 416 kaliber 5.56mm NATO. Prace nad karabinem HK 417 rozpoczêto w roku 2005, bazuj¹c na doœwiadczeniach zdobytych przez wojska koalicji miêdzynarodowej w Afganistanie i Iraku, gdzie w istniej¹cych warunkach broñ kalibru 5.56mm wykaza³a siê niedostatecznie efektywnym zasiêgiem i niewystarczaj¹c¹ si³¹ przebijania ma³okalibrowych pocisków. Karabiny serii HK 417 wesz³y do seryjnej produkcji w 2007 lub 2008 roku, i s¹ przeznaczone na wyposa¿enie si³ wojskowych i policyjnych. Karabin HK 417 ma konstrukcje modu³ow¹, w znacznym stopniu powtarzaj¹c¹ konstrukcjê amerykañskiego karabinu M16, z jedn¹ istotn¹ ró¿nic¹ - niemiecki karabin HK 417 ma zmeniony system automatyki odprowadzania gazów prochowych, wykorzystuj¹cy zwyk³y t³ok gazowy z krótkim skokiem. Jest równie¿ szereg drobniejszych ró¿nic, jednak¿e wszystkie zasadnicze elementy sterowania oraz metoda rozbierania i sk³adania broni s¹ naœladownictwem M16. Wyposa¿ony w celownik optyczny 6x.</text>
	</string>
	<string id="enc_arsenal_galatz">
		<text>Ten karabin snajperski (w Armii Obrony Izraela - CaHaL-e znany pod nazw¹ GALATZ) w rzeczywistoœci jest przeróbk¹ automatu IMI Galil pod mocniejszy nabój 7.62mm NATO (.308win). Z punktu widzenia taktyki, GALATZ jest bli¿szy takim modelom "broni wsparcia", jak rosyjski SWD lub niemiecki G3-SG1, w odróznieniu od "czysto snajperskich" modeli, typu amerykañskich M24 lub M40, albo niemieckich Mauser 66 i 86, tak¿e uzywanych w Armii Obrony Izraela.</text>
	</string>
	<string id="enc_arsenal_svd">
		<text>W 1958 roku GRAU (G³ówne Dowództwo Rakietowo-Artyleryjskie) Sztabu Generalnego Armii Radzieckiej og³osi³o konkurs na opracowanie samopowtarzalnego karabinu snajperskiego dla Armii Radzieckiej. W konkursie zwyciê¿y³ zespó³ pod przewodnictwem E. Dragunowa, i w 1963 roku SWD (Snajperski karabin Dragunowa) by³ przyjêty na uzbrojenia Armii Radzieckiej. Specjalnie dla SWD by³ opracowany "snajperski" nabój z kul¹ ze stalowym rdzeniem, jednak¿e w karabinie mo¿na korzustaæ  z ca³ej nomkenklatury rodzimych nabojów 7.62x54R. Nale¿y zaznaczyæ, ¿e rola taktyczna, która by³a i jest przyznawana karabinowi SWD w Radzieckiej i Rosyjskiej armii rózni siê od tradfycyjnej roli "snajpera" w zachodnim rozumieniu tego s³owa. Karabin SWD s³uzy do powiêkszenia zasiêgu efektywnego ognia oddzia³u strzeleckiego poza zasiêg typowych automatów, a¿ do dystaqnsu 600-700 metrów. Najbardziej rozprzestrzeniony karabin snajperski w Zonie.</text>
	</string>
	<string id="enc_arsenal_acog">
		<text>4-krotny celownik optyczny dla karabinów NATO.</text>
	</string>
	<string id="enc_arsenal_aug_a1_scope">
		<text>Obiektyw celownika optycznego karabinu Steyr AUG-77.</text>
	</string>
	<string id="enc_arsenal_g36_scope">
		<text>Obiektyw celownika optycznego karabinu G36.</text>
	</string>
	<string id="enc_arsenal_scope1">
		<text>Zdejmowany celownik optyczny starego typu do karabinów M16A1\A2.</text>
	</string>
	<string id="enc_arsenal_sil_9_p">
		<text>Urz¹dzenie do bezg³oœnego strzelania dla pistoletów kalibru 9mm.</text>
	</string>
	<string id="enc_arsenal_sil_762_p">
		<text>Urz¹dzenie do bezg³oœnego strzelania dla pistoletów kalibru 7.62mm.</text>
	</string>
	<string id="enc_arsenal_sil_9_pb">
		<text>Urz¹dzenie do bezg³oœnego strzelania dla pistoletu PB (6P9).</text>
	</string>
	<string id="enc_arsenal_sil_545_ar">
		<text>Urz¹dzenie do bezg³oœnego strzelania dla automatów kalibru 5.45mm.</text>
	</string>
	<string id="enc_arsenal_sil_556_ar">
		<text>T³umik  do automatów i karabinów kalibru 5.56mm.</text>
	</string>
	<string id="enc_arsenal_sil_762_ar">
		<text>T³umik  do automatów i karabinów kalibru 7.62mm.</text>
	</string>
	<string id="enc_arsenal_sil_762_pms">
		<text>Przyrz¹d do cichego strzelania dla karabinów kalibru 7.62mm, w szczególnoœci, dla SWD.</text>
	</string>
	<string id="enc_arsenal_sil_1143_p">
		<text>Urz¹dzenie do bezg³oœnego strzelania dla pistoletów kalibru 11.43mm (.45).</text>
	</string>
	<string id="enc_arsenal_50_ae">
		<text>Pistoletowy nabój z kul¹ du¿ego kalibru dla pistoletu Desert Eagle.</text>
	</string>
	<string id="enc_weapons1_ammo_ammo-7.62x25-p">
		<text>Radziecki pistoletowy nabój kalibru 7.62mm. Zwyk³a pe³nop³aszczowa kula.</text>
	</string>
	<string id="enc_weapons1_ammo_ammo-7.62x25-ps">
		<text>Radziecki pistoletowy nabój kalibru 7.62mm. Kula ze stalowym rdzeniem, polepszona si³a przebicia.</text>
	</string>
	<string id="enc_arsenal_7.62x39_fmj">
		<text>Radziecki automatowy nabój kalibru 7.62mm. Zwyk³a pe³nop³aszczowa kula.</text>
	</string>
	<string id="enc_arsenal_7.62x39_ap">
		<text>Radziecki automatowy nabój kalibru 7.62mm. Kula ze stalowym rdzeniem, polepszona si³a przebicia.</text>
	</string>
	<string id="enc_arsenal_7.62x51_fmj">
		<text>Nabój standardu NATO. Kaliber - 7.62mm. Prosta, pe³nometalowa kula.</text>
	</string>
	<string id="enc_arsenal_7.62x51_ap">
		<text>Nabój standardu NATO. Kaliber - 7.62mm. Kula ze stalowym rdzeniem, powiêkszona si³a przebicia.</text>
	</string>
</string_table>