<string id="agr_secret_0000_descr">
    <text>Our stash is in the tunnel for now, all the goods are in a pipe. It's a good spot, few people know about it, and the anomalies will discourage anyone from poking around.</text>
</string>
<string id="agr_secret_0000_name">
    <text>Gray's Stash</text>
</string>
<string id="agr_secret_0001_descr">
    <text>Hid it in the stump near the tunnel. Nice hole there.</text>
</string>
<string id="agr_secret_0001_name">
    <text>Hollow Stump</text>
</string>
<string id="agr_secret_0002_descr">
    <text>Buried some goods under the cross, near the bush.</text>
</string>
<string id="agr_secret_0002_name">
    <text>Stash Under Cross</text>
</string>
<string id="agr_secret_0003_descr">
    <text>Dropped the backpack under a fallen tree.</text>
</string>
<string id="agr_secret_0003_name">
    <text>Backpack Under Tree</text>
</string>
<string id="agr_secret_0004_descr">
    <text>Shoved the backpack into a pipe near the factory. Nobody will find it.</text>
</string>
<string id="agr_secret_0004_name">
    <text>Chimney Sweep's Backpack</text>
</string>
<string id="agr_secret_0005_descr">
    <text>Stashed a box on the factory roof, nobody will see it there. Just hope it doesn't rust in the rain.</text>
</string>
<string id="agr_secret_0005_name">
    <text>Box on the Roof</text>
</string>
<string id="agr_secret_0006_descr">
    <text>Got shot at, had to ditch the backpack under a train car, behind a wheel. At least I got away. I'll pick it up later.</text>
</string>
<string id="agr_secret_0006_name">
    <text>Drunk's Backpack</text>
</string>
<string id="agr_secret_0007_descr">
    <text>Hid it under a cross behind the cisterns. Dig a little, just don't get carried away.</text>
</string>
<string id="agr_secret_0007_name">
    <text>By the Three Cisterns</text>
</string>
<string id="agr_secret_0008_descr">
    <text>Put the backpack up high at the factory so you can't see it from below. Just can't remember exactly what's in it.</text>
</string>
<string id="agr_secret_0008_name">
    <text>Backpack in Porthole</text>
</string>
<string id="agr_secret_0009_descr">
    <text>Hid some stuff inside the factory in a box.</text>
</string>
<string id="agr_secret_0009_name">
    <text>Radioactive Box</text>
</string>
<string id="agr_secret_0010_descr">
    <text>Stash in a box under the stairs.</text>
</string>
<string id="agr_secret_0010_name">
    <text>Box in the Span</text>
</string>
<string id="agr_secret_0011_descr">
    <text>Hid it in a crate, nobody's going to check anyway.</text>
</string>
<string id="agr_secret_0011_name">
    <text>Factory Crate</text>
</string>
<string id="agr_secret_0012_descr">
    <text>Dropped the bag outside the window, I'll grab it later.</text>
</string>
<string id="agr_secret_0012_name">
    <text>Bag on Support</text>
</string>
<string id="agr_secret_0013_descr">
    <text>Me and Kolyan had a good time at Agroprom, grabbed all kinds of junk, but had to stash some of it. Put the box in a dumpster.</text>
</string>
<string id="agr_secret_0013_name">
    <text>Trash Box</text>
</string>
<string id="agr_secret_0014_descr">
    <text>Found a safe under a fallen tree, I'll hide everything there for now.</text>
</string>
<string id="agr_secret_0014_name">
    <text>Safe Under Tree</text>
</string>
<string id="agr_secret_0015_descr">
    <text>Tossed some stuff into a pipe, I'll pick it up later. Had to leave it, would've taken it with me otherwise, of course. Hope it doesn't get wet.</text>
</string>
<string id="agr_secret_0015_name">
    <text>Stuff in the Pipe</text>
</string>
<string id="agr_secret_0016_descr">
    <text>Goods in the old pipe, gotta tell the boys. I ain't going in there.</text>
</string>
<string id="agr_secret_0016_name">
    <text>Radioactive Pipe</text>
</string>
<string id="agr_secret_0017_descr">
    <text>Ran from the base, screw that, I'm not getting shot at by stalkers. Hid my gear in a pipe in the rubble. I'll wait till they leave, then get it.</text>
</string>
<string id="agr_secret_0017_name">
    <text>Rubble</text>
</string>
<string id="agr_secret_0018_descr">
    <text>Half-buried safe under a bush, I hide everything here.</text>
</string>
<string id="agr_secret_0018_name">
    <text>Safe Under Bush</text>
</string>
<string id="agr_secret_0019_descr">
    <text>Found a box under the support, someone dragged it all the way from the research institute. We'll wait for the chopper, then we'll grab it.</text>
</string>
<string id="agr_secret_0019_name">
    <text>Archive Box</text>
</string>
<string id="agr_secret_0020_descr">
    <text>Hid some stuff in the metal container.</text>
</string>
<string id="agr_secret_0020_name">
    <text>Under the Hatch</text>
</string>
<string id="agr_secret_0021_descr">
    <text>Half-buried safe under a bush, I hide everything there.</text>
</string>
<string id="agr_secret_0021_name">
    <text>Under Bush by Wall</text>
</string>
<string id="agr_secret_0022_descr">
    <text>Convenient box to dump excess junk.</text>
</string>
<string id="agr_secret_0022_name">
    <text>Institute Crate</text>
</string>
<string id="agr_secret_0023_descr">
    <text>Hid it in a safe, then the military showed up. Can't get the goods now.</text>
</string>
<string id="agr_secret_0023_name">
    <text>Agro-safe</text>
</string>
<string id="agr_secret_0024_descr">
    <text>Threw my gear in a pipe, I'll pick it up later.</text>
</string>
<string id="agr_secret_0024_name">
    <text>Truck Bed</text>
</string>
<string id="agr_secret_0025_descr">
    <text>Grab the stuff from the rotten log.</text>
</string>
<string id="agr_secret_0025_name">
    <text>Rotten Log</text>
</string>
<string id="agr_secret_0026_descr">
    <text>Convenient box to dump excess junk. Used to store institute maintenance equipment.</text>
</string>
<string id="agr_secret_0026_name">
    <text>Quartermaster's Box</text>
</string>
<string id="agr_secret_0027_descr">
    <text>Handy little box for small items, I used to keep locksmith tools in one like this at home.</text>
</string>
<string id="agr_secret_0027_name">
    <text>Locksmith's Inventory</text>
</string>
<string id="agr_u_secret_0000_descr">
    <text>Bandits are hiding something under a pipe, gotta check it out. From the chatter, it's clear that's where their supplies are.</text>
</string>
<string id="agr_u_secret_0000_name">
    <text>Bandit Common Fund</text>
</string>
<string id="agr_u_secret_0001_descr">
    <text>Hid the backpack behind concrete chunks, traveling light. Better hungry than dead.</text>
</string>
<string id="agr_u_secret_0001_name">
    <text>Backpack in Corner</text>
</string>
<string id="agr_u_secret_0002_descr">
    <text>Box behind a rusty barrel in the underground, everything's there. I'm not going back, no way! How I killed that bloodsucker, I still don't remember.</text>
</string>
<string id="agr_u_secret_0002_name">
    <text>Bloodsucker's Box</text>
</string>
<string id="agr_u_secret_0003_descr">
    <text>Loot's behind the wall. I'm not lying!</text>
</string>
<string id="agr_u_secret_0003_name">
    <text>Stalker's Loot</text>
</string>
<string id="agr_u_secret_0004_descr">
    <text>I dug up some valuables here. Clever spot for my stash. On a yellow barrel, good luck finding it.</text>
</string>
<string id="agr_u_secret_0004_name">
    <text>Mole's Den</text>
</string>
<string id="bar_secret_0000_description">
    <text>Hid the backpack near Duty's base. I'll grab it later.</text>
</string>
<string id="bar_secret_0000_name">
    <text>Hidden Backpack</text>
</string>
<string id="bar_secret_0001_description">
    <text>Got chased by a big pack of dogs, wouldn't have made it to the checkpoint if I hadn't ditched the backpack.</text>
</string>
<string id="bar_secret_0001_name">
    <text>Abandoned Backpack</text>
</string>
<string id="bar_secret_0002_description">
    <text>Whatever's left, we buried under the cross.</text>
</string>
<string id="bar_secret_0002_name">
    <text>Stash Under Cross</text>
</string>
<string id="bar_secret_0003_description">
    <text>Dropped the backpack here, makes it easier to move.</text>
</string>
<string id="bar_secret_0003_name">
    <text>Backpack</text>
</string>
<string id="bar_secret_0004_description">
    <text>Duty checkpoint's gear is stored in the bunker, but nobody watches that box.</text>
</string>
<string id="bar_secret_0004_name">
    <text>Storage in Bunker</text>
</string>
<string id="bar_secret_0005_description">
    <text>Saw a Duty guy shove something into a pipe near the checkpoint.</text>
</string>
<string id="bar_secret_0005_name">
    <text>Stash</text>
</string>
<string id="bar_secret_0006_description">
    <text>It all belonged to him, let it lie here for now.</text>
</string>
<string id="bar_secret_0006_name">
    <text>Stash Under Cross</text>
</string>
<string id="bar_secret_0007_description">
    <text>Going to the bar, left the backpack in the hangar.</text>
</string>
<string id="bar_secret_0007_name">
    <text>Backpack</text>
</string>
<string id="bar_secret_0008_description">
    <text>They say there's something valuable in the electrical panel on Duty territory.</text>
</string>
<string id="bar_secret_0008_name">
    <text>Electrical Panel Stash</text>
</string>
<string id="bar_secret_0009_description">
    <text>Stuffed a little box up on the tower near Duty so nobody will notice.</text>
</string>
<string id="bar_secret_0009_name">
    <text>Stash on Tower</text>
</string>
<string id="bar_secret_0010_description">
    <text>Hid it in a pipe under the stairs.</text>
</string>
<string id="bar_secret_0010_name">
    <text>Stash</text>
</string>
<string id="bar_secret_0011_description">
    <text>Not far from the bar, hid the goods behind anomalies, nobody can get to it. And they don't know how to open it anyway, but it's simple - just pry the door and it'll open right up.</text>
</string>
<string id="bar_secret_0011_name">
    <text>Arnie's Stash</text>
</string>
<string id="bar_secret_0012_description">
    <text>Not far from the bar, hid the goods.</text>
</string>
<string id="bar_secret_0012_name">
    <text>Stash</text>
</string>
<string id="bar_secret_0013_description">
    <text>Near the bar in a box.</text>
</string>
<string id="bar_secret_0013_name">
    <text>Box</text>
</string>
<string id="bar_secret_0014_description">
    <text>In the alley near the bar, hid a little box.</text>
</string>
<string id="bar_secret_0014_name">
    <text>Little Box</text>
</string>
<string id="bar_secret_0015_description">
    <text>Buried under the cross behind the fir trees.</text>
</string>
<string id="bar_secret_0015_name">
    <text>Stash</text>
</string>
<string id="bar_secret_0016_description">
    <text>Under the cross, not far from the passage to Wild Territory.</text>
</string>
<string id="bar_secret_0016_name">
    <text>Stash</text>
</string>
<string id="bar_secret_0017_description">
    <text>In a pipe near the Arena, hid a little box with anti-rad.</text>
</string>
<string id="bar_secret_0017_name">
    <text>Little Box</text>
</string>
<string id="bar_secret_0018_description">
    <text>Under the tower, hid my gear in a pipe.</text>
</string>
<string id="bar_secret_0018_name">
    <text>Stash</text>
</string>
<string id="bar_secret_0019_description">
    <text>Stash under the cross.</text>
</string>
<string id="bar_secret_0019_name">
    <text>Stash</text>
</string>
<string id="esc_secret_0000_descr">
    <text>During regrouping, hid the ammunition. Don't forget.</text>
</string>
<string id="esc_secret_0000_name">
    <text>Common Box</text>
</string>
<string id="esc_secret_0001_descr">
    <text>Saw some stalker get killed by an anomaly near the railway tunnel in the woods, looked like he had decent gear.</text>
</string>
<string id="esc_secret_0001_name">
    <text>Dead Man's Belongings in Anomaly</text>
</string>
<string id="esc_secret_0002_descr">
    <text>Hid the loot in the trailer.</text>
</string>
<string id="esc_secret_0002_name">
    <text>Trailer</text>
</string>
<string id="esc_secret_0003_descr">
    <text>Noticed the bandits left some supplies at the bus station when they left the auto park.</text>
</string>
<string id="esc_secret_0003_name">
    <text>Bandit Warehouse</text>
</string>
<string id="esc_secret_0004_descr">
    <text>When me and the boys were fighting off dogs in uniforms, I stashed some goods at the temporary camp. Let it lie there.</text>
</string>
<string id="esc_secret_0004_name">
    <text>Temporary Camp</text>
</string>
<string id="esc_secret_0005_descr">
    <text>Left the backpack where I took a short break. I'll come back later, can't do it now.</text>
</string>
<string id="esc_secret_0005_name">
    <text>Rest Stop Stash</text>
</string>
<string id="esc_secret_0006_descr">
    <text>Found a half-buried safe at the farm, I'll store the goods there for now.</text>
</string>
<string id="esc_secret_0006_name">
    <text>Safe at the Farm</text>
</string>
<string id="esc_secret_0007_descr">
    <text>Stashed it in the safe at our camp, reserve for a rainy day.</text>
</string>
<string id="esc_secret_0007_name">
    <text>Supplies in Safe</text>
</string>
<string id="esc_secret_0008_descr">
    <text>Hid the goods by the tunnel, the one with the electros.</text>
</string>
<string id="esc_secret_0008_name">
    <text>Stalker's Goods</text>
</string>
<string id="esc_secret_0009_descr">
    <text>Hid my gear in one of the boxes near the bridge. That's it, I'm done. Leaving the Zone, farewell brothers! Won't forget my dear mother.</text>
</string>
<string id="esc_secret_0009_name">
    <text>Stuff Near Bridge</text>
</string>
<string id="esc_secret_0010_descr">
    <text>Some stalker died not far from the rookie camp, dumped his gear in a box nearby.</text>
</string>
<string id="esc_secret_0010_name">
    <text>Box by the Village</text>
</string>
<string id="esc_secret_0011_descr">
    <text>Stash in the attic, learned about it from Dashing. He ran his mouth too much, so we whacked him.</text>
</string>
<string id="esc_secret_0011_name">
    <text>Attic in Village</text>
</string>
<string id="esc_secret_0012_descr">
    <text>Found an excellent stash in a pipe, I'll wait for someone to put something there.</text>
</string>
<string id="esc_secret_0012_name">
    <text>Convenient Spot</text>
</string>
<string id="esc_secret_0013_descr">
    <text>Stash in the attic, learned about it from Vorpal. Our guys were scouting the area. Let's check it out.</text>
</string>
<string id="esc_secret_0013_name">
    <text>Vorpal's Stash</text>
</string>
<string id="esc_secret_0014_descr">
    <text>They say the commander has a clever box in his office, and there's tons of valuable stuff in it.</text>
</string>
<string id="esc_secret_0014_name">
    <text>Commander's Valuables</text>
</string>
<string id="esc_secret_0015_descr">
    <text>Dumped my stuff in a stump, once I shake the Military, I'll come back for it.</text>
</string>
<string id="esc_secret_0015_name">
    <text>In the Stump</text>
</string>
<string id="esc_secret_0016_descr">
    <text>Some stalker died not far from the rookie camp, should check what he was carrying. Who even lets them in here?</text>
</string>
<string id="esc_secret_0016_name">
    <text>By the Country Road</text>
</string>
<string id="esc_secret_0017_descr">
    <text>Found inventory in a box not far from the farm. Once guardhouse duty is over - I'll definitely come back.</text>
</string>
<string id="esc_secret_0017_name">
    <text>Behind the Farm</text>
</string>
<string id="esc_secret_0018_descr">
    <text>Dropped the backpack not far from the post, gotta grab it quick before the commander transfers us to another location.</text>
</string>
<string id="esc_secret_0018_name">
    <text>Hidden Things</text>
</string>
<string id="esc_secret_0019_descr">
    <text>Temporarily left a box at the checkpoint. I'll grab it when I can.</text>
</string>
<string id="esc_secret_0019_name">
    <text>Stash at Checkpoint</text>
</string>
<string id="gar_secret_0000_descr">
    <text>Saw a bandit hiding his goods in a hangar in a box. How can I quietly swipe it?</text>
</string>
<string id="gar_secret_0000_name">
    <text>Bandit Stash</text>
</string>
<string id="gar_secret_0001_descr">
    <text>Me and Vasya went to check things out, and Vasya caught a cop bullet. I had nothing to do with it. Bullet's stupid. Stashed his stuff on the crane in a pipe.</text>
</string>
<string id="gar_secret_0001_name">
    <text>Old Crane</text>
</string>
<string id="gar_secret_0002_descr">
    <text>In the Garbage, in the railway tunnel behind the diesel, Grizzly bought it with all his junk. Poor guy.</text>
</string>
<string id="gar_secret_0002_name">
    <text>Grizzly's Stuff</text>
</string>
<string id="gar_secret_0003_descr">
    <text>Stashed the loot in a pipe at the dump.</text>
</string>
<string id="gar_secret_0003_name">
    <text>Pipe on North Heap</text>
</string>
<string id="gar_secret_0004_descr">
    <text>Stuff is in the dump, in the electrical panel.</text>
</string>
<string id="gar_secret_0004_name">
    <text>Stash in Scrap Metal</text>
</string>
<string id="gar_secret_0005_descr">
    <text>Hid the junk in a metal pipe near two cisterns. Should grab it, but no time.</text>
</string>
<string id="gar_secret_0005_name">
    <text>Cast Iron by Cisterns</text>
</string>
<string id="gar_secret_0006_descr">
    <text>Among the radioactive trash where few people wander, some useful stuff is hidden.</text>
</string>
<string id="gar_secret_0006_name">
    <text>Pipe on East Heap</text>
</string>
<string id="gar_secret_0007_descr">
    <text>Someone's backpack is lying in the lowland, surrounded by anomalies. How to get to it?</text>
</string>
<string id="gar_secret_0007_name">
    <text>Unclaimed Backpack</text>
</string>
<string id="gar_secret_0008_descr">
    <text>Whacked a snitch at the swamp, buried him there. Left his loot under a cross, didn't have time for it.</text>
</string>
<string id="gar_secret_0008_name">
    <text>Dead Man's Belongings</text>
</string>
<string id="gar_secret_0009_descr">
    <text>Stash in the stump, good spot.</text>
</string>
<string id="gar_secret_0009_name">
    <text>Rotten Stump</text>
</string>
<string id="gar_secret_0010_descr">
    <text>In the woods a stump, inside - a hole. In it treasure, time to take it whole.</text>
</string>
<string id="gar_secret_0010_name">
    <text>Stump in Woods</text>
</string>
<string id="gar_secret_0011_descr">
    <text>Petrenko passed word that there's info about a stalker group's stash at the Garbage. There should be a hatch in the lowland. He told me how to cleverly open it. Once things settle down, gotta head there.</text>
</string>
<string id="gar_secret_0011_name">
    <text>Stalker Group Warehouse</text>
</string>
<string id="gar_secret_0012_descr">
    <text>Stashed it in a log, Long said it's a good spot.</text>
</string>
<string id="gar_secret_0012_name">
    <text>Stash in Log</text>
</string>
<string id="gar_secret_0013_descr">
    <text>Put the backpack in the bus, seems inconspicuous.</text>
</string>
<string id="gar_secret_0013_name">
    <text>Stalker's Backpack in Bus</text>
</string>
<string id="gar_secret_0014_descr">
    <text>Packed supplies in a backpack, under a military corpse.</text>
</string>
<string id="gar_secret_0014_name">
    <text>Military Supplies</text>
</string>
<string id="gar_secret_0015_descr">
    <text>On the trash heap is a half-buried safe, that's where it all is. Hope I don't forget what exactly.</text>
</string>
<string id="gar_secret_0015_name">
    <text>Safe on South Heap</text>
</string>
<string id="gar_secret_0016_descr">
    <text>On the trash heap in a pipe, put the loot.</text>
</string>
<string id="gar_secret_0016_name">
    <text>Stash in Scrap</text>
</string>
<string id="gar_secret_0017_descr">
    <text>Commander ordered retreat over radio. I stumbled on a box, dumped excess weight in it and withdrew light.</text>
</string>
<string id="gar_secret_0017_name">
    <text>Supply in Box</text>
</string>
<string id="gar_secret_0018_descr">
    <text>Shoved the loot in a box at the dump. Won't last there long.</text>
</string>
<string id="gar_secret_0018_name">
    <text>Stash on Excavator</text>
</string>
<string id="gar_secret_0019_descr">
    <text>Hid the backpack well in the ruins. Hope it'll be easy to grab if bandits don't interfere.</text>
</string>
<string id="gar_secret_0019_name">
    <text>Backpack in Ruins</text>
</string>
<string id="gar_secret_0020_descr">
    <text>While Duty guys were shooting, stashed the loot in a trailer. Gotta somehow get in and grab it. And say thanks to Duty.</text>
</string>
<string id="gar_secret_0020_name">
    <text>Box at Checkpoint</text>
</string>
<string id="gar_secret_0021_descr">
    <text>They say Deadman croaked at the Garbage, gotta visit, check out the loot. Lots of people will be rushing there.</text>
</string>
<string id="gar_secret_0021_name">
    <text>Deadman's Backpack</text>
</string>
<string id="gar_secret_0022_descr">
    <text>I'll hide the goods in the stump for now, maybe they won't find it.</text>
</string>
<string id="gar_secret_0022_name">
    <text>Maybe Bag in Stump</text>
</string>
<string id="gar_secret_0023_descr">
    <text>Near the excavator, someone died in an anomaly, got his junk and hid it in a stump.</text>
</string>
<string id="gar_secret_0023_name">
    <text>Stump Under Hill</text>
</string>
<string id="gar_secret_0024_descr">
    <text>Barely squeezed under the beams, but hid the backpack well, nobody will climb in here.</text>
</string>
<string id="gar_secret_0024_name">
    <text>Stash Under Concrete Blocks</text>
</string>
<string id="mil_secret_0000_description">
    <text>Shoved the goods in a log, don't think they'll find it.</text>
</string>
<string id="mil_secret_0000_name">
    <text>Stash in Log</text>
</string>
<string id="mil_secret_0001_description">
    <text>Stashed some junk in the stove.</text>
</string>
<string id="mil_secret_0001_name">
    <text>Stash in Stove</text>
</string>
<string id="mil_secret_0002_description">
    <text>Stashed some junk in the KAMAZ cab.</text>
</string>
<string id="mil_secret_0002_name">
    <text>Stash in KAMAZ</text>
</string>
<string id="mil_secret_0003_description">
    <text>Buried some loot under the cross near the village.</text>
</string>
<string id="mil_secret_0003_name">
    <text>Treasure Under Cross</text>
</string>
<string id="mil_secret_0004_description">
    <text>Threw my gear in a box, I'll grab it later.</text>
</string>
<string id="mil_secret_0004_name">
    <text>Stash in Box</text>
</string>
<string id="mil_secret_0005_description">
    <text>Stash in the water tower, in a box.</text>
</string>
<string id="mil_secret_0005_name">
    <text>Treasure in Tower</text>
</string>
<string id="mil_secret_0006_description">
    <text>Dumped excess in a box, will come in handy later.</text>
</string>
<string id="mil_secret_0006_name">
    <text>Stash in Box</text>
</string>
<string id="mil_secret_0007_description">
    <text>Hid the loot in a car in the abandoned village.</text>
</string>
<string id="mil_secret_0007_name">
    <text>Car Stash</text>
</string>
<string id="mil_secret_0008_description">
    <text>Left the backpack in radioactive ruins. They'll be too scared to go in.</text>
</string>
<string id="mil_secret_0008_name">
    <text>Dangerous Secret</text>
</string>
<string id="mil_secret_0009_description">
    <text>Buried the loot under a cross in a secluded spot.</text>
</string>
<string id="mil_secret_0009_name">
    <text>Stalker's Stash</text>
</string>
<string id="mil_secret_0010_description">
    <text>Stashed a little backpack with gear in a secluded spot.</text>
</string>
<string id="mil_secret_0010_name">
    <text>Backpack with Gear</text>
</string>
<string id="mil_secret_0011_description">
    <text>Stashed my gear on the hill in a car.</text>
</string>
<string id="mil_secret_0011_name">
    <text>Stash on Hill</text>
</string>
<string id="mil_secret_0012_description">
    <text>A helicopter crashed near the abandoned military base, the box is lying nearby, right under the chopper. One problem - anomalies and radiation all around.</text>
</string>
<string id="mil_secret_0012_name">
    <text>Box from Helicopter</text>
</string>
<string id="mil_secret_0013_description">
    <text>Buried the loot on the hill under a cross.</text>
</string>
<string id="mil_secret_0013_name">
    <text>Secret in Grave</text>
</string>
<string id="mil_secret_0014_description">
    <text>Stash in the stump, good spot.</text>
</string>
<string id="mil_secret_0014_name">
    <text>Secret Stump</text>
</string>
<string id="mil_secret_0015_description">
    <text>Left the backpack in the crane cab, I'll grab it later.</text>
</string>
<string id="mil_secret_0015_name">
    <text>Highrise Worker's Stash</text>
</string>
<string id="mil_secret_0016_description">
    <text>Put everything in a box in a train car not far from the base. That's what we agreed on, now all that's left is to wait.</text>
</string>
<string id="mil_secret_0016_name">
    <text>Agreed Stash</text>
</string>
<string id="mil_secret_0017_description">
    <text>Shoved the goods in a log, don't think they'll find it.</text>
</string>
<string id="mil_secret_0017_name">
    <text>Treasure in Log</text>
</string>
<string id="mil_secret_0018_description">
    <text>Shoved the loot in a pipe by the lake shore.</text>
</string>
<string id="mil_secret_0018_name">
    <text>Pipe with Loot</text>
</string>
<string id="mil_secret_0019_description">
    <text>Hid some stuff in the metal container.</text>
</string>
<string id="mil_secret_0019_name">
    <text>Stalker's Stash</text>
</string>
<string id="mil_secret_0020_description">
    <text>Shoved the goods in a log, don't think they'll find it.</text>
</string>
<string id="mil_secret_0020_name">
    <text>Loot in Log</text>
</string>
<string id="mil_secret_0021_description">
    <text>Convenient box to dump excess junk.</text>
</string>
<string id="mil_secret_0021_name">
    <text>Convenient Stash</text>
</string>
<string id="mil_secret_0022_description">
    <text>Stashed a backpack with loot in the tunnel.</text>
</string>
<string id="mil_secret_0022_name">
    <text>Backpack in Tunnel</text>
</string>
<string id="mil_secret_0023_description">
    <text>Convenient box to dump excess junk.</text>
</string>
<string id="mil_secret_0023_name">
    <text>Box with Goods</text>
</string>
<string id="mil_secret_0024_description">
    <text>Shoved the goods in a log, don't think they'll find it.</text>
</string>
<string id="mil_secret_0024_name">
    <text>Stash in Log</text>
</string>
<string id="mil_secret_0025_description">
    <text>Tossed the goods in a box, I'll grab it later.</text>
</string>
<string id="mil_secret_0025_name">
    <text>Temporary Stash</text>
</string>
<string id="mil_secret_0026_description">
    <text>Stashed things in the hatch, will come in handy someday.</text>
</string>
<string id="mil_secret_0026_name">
    <text>Steel Stash</text>
</string>
<string id="mil_secret_0027_description">
    <text>Tossed the goods in a box, I'll grab it later.</text>
</string>
<string id="mil_secret_0027_name">
    <text>Box with Loot</text>
</string>
<string id="mil_secret_0028_description">
    <text>Hid the loot in a car right under Freedom's nose, didn't have time to look for something better.</text>
</string>
<string id="mil_secret_0028_name">
    <text>Stash in Car</text>
</string>
<string id="pri_secret_0000_description">
    <text>They say some famous stalker died here, his goods still haven't been picked up by anyone.</text>
</string>
<string id="pri_secret_0000_name">
    <text>Dead Stalker's Belongings</text>
</string>
<string id="pri_secret_0001_description">
    <text>In the garage, they say there's a box, and it's got tons of loot.</text>
</string>
<string id="pri_secret_0001_name">
    <text>Treasure in Garage</text>
</string>
<string id="pri_secret_0002_description">
    <text>In the kindergarten, they say there's a box, and it's got tons of loot.</text>
</string>
<string id="pri_secret_0002_name">
    <text>Old Stash</text>
</string>
<string id="pri_secret_0003_description">
    <text>In Pripyat, under the monument. Left all the loot as is - not right to take from the dead.</text>
</string>
<string id="pri_secret_0003_name">
    <text>Dead Man's Loot</text>
</string>
<string id="pri_secret_0004_description">
    <text>The last thing known about him was that he was the only survivor after the "Burner." Left supplies in some former department store and moved on. Everything went wrong as planned, and he was the best Freedom leader in our entire history.</text>
</string>
<string id="pri_secret_0004_name">
    <text>Freedom Leader's Supplies</text>
</string>
<string id="rad_secret_0000_description">
    <text>Cross on the way to the Burner, didn't go further, hid everything under it.</text>
</string>
<string id="rad_secret_0000_name">
    <text>Grim's Treasure</text>
</string>
<string id="rad_secret_0001_description">
    <text>Some stalker died here, loot's still lying around, nobody can pick it up.</text>
</string>
<string id="rad_secret_0001_name">
    <text>Dead Stalker's Loot</text>
</string>
<string id="rad_secret_0002_description">
    <text>They say there's a half-buried safe in the woods, and it's full of loot.</text>
</string>
<string id="rad_secret_0002_name">
    <text>Loot in Safe</text>
</string>
<string id="rad_secret_0003_description">
    <text>Told them not to fly over the Burner, here's the result. Landed in the middle of the forest, doubt anyone survived. Somewhere there lies what they were delivering to us.</text>
</string>
<string id="rad_secret_0003_name">
    <text>Package for Duty</text>
</string>
<string id="rad_secret_0004_description">
    <text>They say the supplies of a group that was pushing to the center of the Zone right under the Burner's radiation are still there. None of them came back, and the supplies remained waiting for someone to pick them up.</text>
</string>
<string id="rad_secret_0004_name">
    <text>Desperate Group's Supplies</text>
</string>
<string id="rad_secret_0005_description">
    <text>They say the leader of some former faction died here, and he had rich loot with him.</text>
</string>
<string id="rad_secret_0005_name">
    <text>Faction Leader's Loot</text>
</string>
<string id="ros_secret_0000_description">
    <text>Stashed the backpack behind an iron sheet.</text>
</string>
<string id="ros_secret_0000_name">
    <text>Hidden Backpack</text>
</string>
<string id="ros_secret_0001_description">
    <text>Hid the goods under a cross.</text>
</string>
<string id="ros_secret_0001_name">
    <text>Stash Under Cross</text>
</string>
<string id="ros_secret_0002_description">
    <text>Hid something in a box under the shed. Don't forget.</text>
</string>
<string id="ros_secret_0002_name">
    <text>Box Under Shed</text>
</string>
<string id="ros_secret_0003_description">
    <text>Shoved the backpack under the steps, then those bastards showed up. Damn, how do I get it?</text>
</string>
<string id="ros_secret_0003_name">
    <text>Stalker's Backpack</text>
</string>
<string id="ros_secret_0004_description">
    <text>Here in the corner behind a tree is a half-buried safe, my junk can stay here.</text>
</string>
<string id="ros_secret_0004_name">
    <text>Stash Behind Tree</text>
</string>
<string id="ros_secret_0005_description">
    <text>Everything we captured during the raid, hid in a box in the garage.</text>
</string>
<string id="ros_secret_0005_name">
    <text>Stash in Garage</text>
</string>
<string id="ros_secret_0006_description">
    <text>Stashed some stuff in a box behind the booth.</text>
</string>
<string id="ros_secret_0006_name">
    <text>Hidden Box</text>
</string>
<string id="ros_secret_0007_description">
    <text>Shoved the backpack in a hole, doesn't seem visible from above.</text>
</string>
<string id="ros_secret_0007_name">
    <text>Backpack in Stash</text>
</string>
<string id="ros_secret_0008_description">
    <text>Stashed a little box in a secluded spot.</text>
</string>
<string id="ros_secret_0008_name">
    <text>Box in Secluded Spot</text>
</string>
<string id="ros_secret_0009_description">
    <text>My backpack lies under the roof. That's for a rainy day.</text>
</string>
<string id="ros_secret_0009_name">
    <text>Stalker's Stash</text>
</string>
<string id="ros_secret_0010_description">
    <text>They say there's a safe in this shed, and something's hidden in it.</text>
</string>
<string id="ros_secret_0010_name">
    <text>Safe in House</text>
</string>
<string id="ros_secret_0011_description">
    <text>Hid it in the shed, in a pipe. Careful, everything's hot there.</text>
</string>
<string id="ros_secret_0011_name">
    <text>Stash in Pipe</text>
</string>
<string id="ros_secret_0012_description">
    <text>What we agreed on, you'll find in the little box, nobody usually looks there.</text>
</string>
<string id="ros_secret_0012_name">
    <text>Hidden Little Box</text>
</string>
<string id="ros_secret_0013_description">
    <text>Hid it under a cross in the alley.</text>
</string>
<string id="ros_secret_0013_name">
    <text>Stash Under Cross</text>
</string>
<string id="ros_secret_0014_description">
    <text>Hid extra supplies at the construction site, under concrete.</text>
</string>
<string id="ros_secret_0014_name">
    <text>Stash Under Concrete</text>
</string>
<string id="ros_secret_0015_description">
    <text>We'll put loot in a box at the construction site, in case we need to run.</text>
</string>
<string id="ros_secret_0015_name">
    <text>Lucky's Stash</text>
</string>
<string id="ros_secret_0016_description">
    <text>Hid it at the construction site in the alley.</text>
</string>
<string id="ros_secret_0016_name">
    <text>Hideout</text>
</string>
<string id="ros_secret_0017_description">
    <text>Stuffed everything in some pipe, we'll grab it later.</text>
</string>
<string id="ros_secret_0017_name">
    <text>Stash in Pipe</text>
</string>
<string id="ros_secret_0018_description">
    <text>Not far from the construction site, hid medicine in a box.</text>
</string>
<string id="ros_secret_0018_name">
    <text>Box with Medicine</text>
</string>
<string id="ros_secret_0019_description">
    <text>Dragged a box into the crane cab.</text>
</string>
<string id="ros_secret_0019_name">
    <text>Box on Crane</text>
</string>
<string id="ros_secret_0020_description">
    <text>In the corner behind the railway, locked my goods in a hatch.</text>
</string>
<string id="ros_secret_0020_name">
    <text>Stash in Hatch</text>
</string>
<string id="ros_secret_0021_description">
    <text>Went for an artifact and got hit by an anomaly, barely walking. Dropped the backpack in the corner behind the railway.</text>
</string>
<string id="ros_secret_0021_name">
    <text>Abandoned Backpack</text>
</string>
<string id="ros_secret_0022_description">
    <text>Up high, under the roof near the tower, stuffed a little box so nobody would notice.</text>
</string>
<string id="ros_secret_0022_name">
    <text>Little Box Under Roof</text>
</string>
<string id="ros_secret_0023_description">
    <text>What we found, hid in a pipe not far from the construction site.</text>
</string>
<string id="ros_secret_0023_name">
    <text>Stash in Pipe</text>
</string>
<string id="ros_secret_0024_description">
    <text>Shoved the goods in a log, don't think they'll find it.</text>
</string>
<string id="ros_secret_0024_name">
    <text>Stash</text>
</string>
<string id="ros_secret_0025_description">
    <text>Stashed a backpack near the crane.</text>
</string>
<string id="ros_secret_0025_name">
    <text>Backpack</text>
</string>
<string id="val_secret_0000_description">
    <text>Buried some loot under the cross near the mountain.</text>
</string>
<string id="val_secret_0000_name">
    <text>Stash Under Cross</text>
</string>
<string id="val_secret_0001_description">
    <text>Shoved the goods in a stump, don't think they'll find it.</text>
</string>
<string id="val_secret_0001_name">
    <text>Stash in Stump</text>
</string>
<string id="val_secret_0002_description">
    <text>Near the bridge, shoved my gear in a stump, let it lie there for now.</text>
</string>
<string id="val_secret_0002_name">
    <text>Stash by Bridge</text>
</string>
<string id="val_secret_0003_description">
    <text>Put a box in a car by the swamp.</text>
</string>
<string id="val_secret_0003_name">
    <text>Car with Stash</text>
</string>
<string id="val_secret_0004_description">
    <text>Stash in the stump, good spot.</text>
</string>
<string id="val_secret_0004_name">
    <text>Stash in Little Stump</text>
</string>
<string id="val_secret_0005_description">
    <text>Found an excellent box at the farm, I'll store supplies there for now.</text>
</string>
<string id="val_secret_0005_name">
    <text>Box with Supplies</text>
</string>
<string id="val_secret_0006_description">
    <text>Threw my gear in a pipe, I'll grab it later.</text>
</string>
<string id="val_secret_0006_name">
    <text>Stash in Pipe</text>
</string>
<string id="val_secret_0007_description">
    <text>Hid things, nobody will find them.</text>
</string>
<string id="val_secret_0007_name">
    <text>Stash in Secret Camp</text>
</string>
<string id="val_secret_0008_description">
    <text>The rookie swiped a box from the bandits. Says it looks like a government box. Gotta gear up the boys and grab it.</text>
</string>
<string id="val_secret_0008_name">
    <text>Government Box</text>
</string>
<string id="val_secret_0009_description">
    <text>Thieves everywhere, even stealing from their own, but they won't find my backpack.</text>
</string>
<string id="val_secret_0009_name">
    <text>Backpack</text>
</string>
<string id="val_secret_0010_description">
    <text>Stashed things on the tower, will come in handy someday.</text>
</string>
<string id="val_secret_0010_name">
    <text>Stash on Tower</text>
</string>
<string id="val_secret_0011_description">
    <text>Dropped the backpack by a soldier's corpse, otherwise wouldn't have escaped the bandits.</text>
</string>
<string id="val_secret_0011_name">
    <text>Backpack by Soldier</text>
</string>
<string id="val_secret_0012_description">
    <text>Put my junk in a dead stalker's backpack, I'll grab it later.</text>
</string>
<string id="val_secret_0012_name">
    <text>Stash</text>
</string>
<string id="val_secret_0013_description">
    <text>Everything I swiped from Borov, hid in the safe under the fir tree. Now gotta wait it out while they're all on edge.</text>
</string>
<string id="val_secret_0013_name">
    <text>Hidden Safe</text>
</string>
<string id="val_secret_0014_description">
    <text>Temporary stash in a pipe.</text>
</string>
<string id="val_secret_0014_name">
    <text>Storage in Pipe</text>
</string>
<string id="val_secret_0015_description">
    <text>Found an inconspicuous spot, now there's a place to hide loot.</text>
</string>
<string id="val_secret_0015_name">
    <text>Secret Spot in Stump</text>
</string>
<string id="val_secret_0016_description">
    <text>Tossed the goods in a box, we'll grab it later.</text>
</string>
<string id="val_secret_0016_name">
    <text>Box with Goods</text>
</string>
<string id="val_secret_0017_description">
    <text>Hiding loot in the water tower. Hard to get to, but they won't steal it.</text>
</string>
<string id="val_secret_0017_name">
    <text>Stash</text>
</string>
<string id="val_secret_0018_description">
    <text>Stashed my gear in a safe.</text>
</string>
<string id="val_secret_0018_name">
    <text>Stash in Safe</text>
</string>
<string id="val_secret_0019_description">
    <text>Everything we found, left in a box, we'll go back and grab it.</text>
</string>
<string id="val_secret_0019_name">
    <text>Box-Stash</text>
</string>
<string id="val_secret_0020_description">
    <text>Stashed the rookie's stuff in a pipe, he never found it.</text>
</string>
<string id="val_secret_0020_name">
    <text>Hidden Things</text>
</string>
<string id="val_secret_0021_description">
    <text>A box was left in the bus, gotta grab it.</text>
</string>
<string id="val_secret_0021_name">
    <text>Forgotten Box</text>
</string>
<string id="val_secret_0022_description">
    <text>Found a safe at the construction site, hid the goods there, seems like few people come here.</text>
</string>
<string id="val_secret_0022_name">
    <text>Safe at Construction Site</text>
</string>
<string id="val_secret_0023_description">
    <text>Dragged a box onto the cistern.</text>
</string>
<string id="val_secret_0023_name">
    <text>Box</text>
</string>
<string id="val_secret_0024_description">
    <text>Hid supplies in a safe at the abandoned construction site.</text>
</string>
<string id="val_secret_0024_name">
    <text>Box at Construction Site</text>
</string>
<string id="val_secret_0025_description">
    <text>By the construction site, someone's box is lying there, gotta sneak through quietly, I sense there's something good to grab.</text>
</string>
<string id="val_secret_0025_name">
    <text>Box</text>
</string>
<string id="val_secret_0026_description">
    <text>Put a box in the stash, reliable spot.</text>
</string>
<string id="val_secret_0026_name">
    <text>Box in Stash</text>
</string>
<string id="val_secret_0027_description">
    <text>Left a box in an abandoned building, good thing nobody's around.</text>
</string>
<string id="val_secret_0027_name">
    <text>Left Box</text>
</string>
<string id="val_secret_0028_description">
    <text>We'll store the goods in a safe in an inconspicuous place. The military will come any day now, they'll tear everyone a new one, but they won't search long, so the most valuable stuff will stay with me.</text>
</string>
<string id="val_secret_0028_name">
    <text>Borov's Stash</text>
</string>
<string id="val_secret_0029_description">
    <text>Stashed a backpack near the building.</text>
</string>
<string id="val_secret_0029_name">
    <text>Backpack in Secret Spot</text>
</string>
<string id="val_secret_0030_description">
    <text>Shoved the loot in an inconspicuous box, I'll grab it later.</text>
</string>
<string id="val_secret_0030_name">
    <text>Inconspicuous Box</text>
</string>
<string id="val_secret_0031_description">
    <text>Hid the loot in an abandoned mini camp, nobody will go there.</text>
</string>
<string id="val_secret_0031_name">
    <text>Hidden Loot</text>
</string>
<string id="val_secret_0032_description">
    <text>Hid the loot right under the bandits' noses, didn't have time to look for something better.</text>
</string>
<string id="val_secret_0032_name">
    <text>Stash Under Tunnel</text>
</string>
<string id="x16_secret_0000_description">
    <text>Rumors say there was a stalker who infiltrated this lab and stashed his loot in the electrical panel in the elevator shaft. But couldn't retrieve it.</text>
</string>
<string id="x16_secret_0000_name">
    <text>Loot in Electrical Panel</text>
</string>
<string id="x16_secret_0001_description">
    <text>Rumors say there was a stalker who infiltrated this lab, and he kicked the bucket near the cages with test subjects with all his loot.</text>
</string>
<string id="x16_secret_0001_name">
    <text>Scout's Backpack</text>
</string>
<string id="x18_secret_0000_description">
    <text>In the underground lab, Smoked put everything in a safe. Good spot, nobody has keys to the lab. One problem - rocks suddenly fly through the air for no reason, they say someone got killed.</text>
</string>
<string id="x18_secret_0000_name">
    <text>Smoked's Stash</text>
</string>
<string id="x18_secret_0001_description">
    <text>Had to drop the backpack.</text>
</string>
<string id="x18_secret_0001_name">
    <text>Abandoned Backpack</text>
</string>
<string id="yan_secret_0000_description">
    <text>Cross on the hill, with a stash underneath.</text>
</string>
<string id="yan_secret_0000_name">
    <text>Stash Under Cross</text>
</string>
<string id="yan_secret_0001_description">
    <text>They say there's a half-buried safe on an island in the swamp. Gotta check it out.</text>
</string>
<string id="yan_secret_0001_name">
    <text>Old Safe</text>
</string>
<string id="yan_secret_0002_description">
    <text>Shoved the goods in a pipe near the camp.</text>
</string>
<string id="yan_secret_0002_name">
    <text>Pipe with Goods</text>
</string>
<string id="yan_secret_0003_description">
    <text>Stashed some loot behind the garages.</text>
</string>
<string id="yan_secret_0003_name">
    <text>Backpack Behind Garages</text>
</string>
<string id="yan_secret_0004_description">
    <text>Stashed the backpack in the booth, right behind the metal thing.</text>
</string>
<string id="yan_secret_0004_name">
    <text>Backpack with Loot</text>
</string>
<string id="yan_secret_0005_description">
    <text>Put a little box in the bus, seems inconspicuous.</text>
</string>
<string id="yan_secret_0005_name">
    <text>Stash in Bus</text>
</string>
<string id="yan_secret_0006_description">
    <text>Loot's hidden in a car not far from the area. Radiation isn't too strong.</text>
</string>
<string id="yan_secret_0006_name">
    <text>Loot in Car</text>
</string>
<string id="yan_secret_0007_description">
    <text>They say there's someone's loot here, just can't get through the emission.</text>
</string>
<string id="yan_secret_0007_name">
    <text>Old Backpack</text>
</string>
<string id="yan_secret_0008_description">
    <text>They say there's some faction's stash here, how did they get through the emission?</text>
</string>
<string id="yan_secret_0008_name">
    <text>Faction Stash</text>
</string>
<string id="yan_secret_0009_description">
    <text>Another volunteer died, another prototype didn't protect from emission. Could only make it to the middle of the area, stayed there. Sakharov wants more precise readings, but I'm not going, or I'll end up there too, not far from the area.</text>
</string>
<string id="yan_secret_0009_name">
    <text>Tester's Backpack</text>
</string>
<string id="yan_secret_0010_description">
    <text>They say there's someone's loot here, just can't get through the emission.</text>
</string>
<string id="yan_secret_0010_name">
    <text>Old Stash</text>
</string>
<string id="yan_secret_0011_description">
    <text>Gotta get out. Sakharov and Kruglov are complete psychos, demanding I go with some stalker to the center of the emission. Screw them, as soon as I collect all the supplies in the hatch, I'm out of here.</text>
</string>
<string id="yan_secret_0011_name">
    <text>Scientist's Stash</text>
</string>
<string id="yan_secret_0012_description">
    <text>Shoved the goods in a log, don't think they'll find it.</text>
</string>
<string id="yan_secret_0012_name">
    <text>Treasure in Log</text>
</string>
<string id="yan_secret_0013_description">
    <text>They say there's someone's stash here, just can't get through the emission.</text>
</string>
<string id="yan_secret_0013_name">
    <text>Box with Goods</text>
</string>

<string id="red_secret_all_name">
    <text>Stash</text>
</string>
<string id="red_secret_all_desc">
    <text>test</text>
</string>

<string id="st_found_new_treasure">
    <text>Information about stash</text>
</string>
